<?xml version="1.0" encoding="UTF-8"?>

<beans xmlns="http://www.springframework.org/schema/beans"
       xmlns:xsi="http://www.w3.org/2001/XMLSchema-instance"
       xsi:schemaLocation="http://www.springframework.org/schema/beans http://www.springframework.org/schema/beans/spring-beans-2.0.xsd">

    <bean name="managerEditorConfigurer" class="org.springframework.beans.factory.config.CustomEditorConfigurer">
        <property name="customEditors">
            <map>
                <entry key="org.jahia.services.uicomponents.bean.contentmanager.Column">
                    <bean class="org.jahia.services.uicomponents.bean.contentmanager.ColumnPropertyEditor"/>
                </entry>
                <entry key="org.jahia.services.uicomponents.bean.contentmanager.Repository">
                    <bean class="org.jahia.services.uicomponents.bean.contentmanager.RepositoryPropertyEditor"/>
                </entry>
            </map>
        </property>
    </bean>

    <!-- file manager -->
    <bean id="filemanager" class="org.jahia.services.uicomponents.bean.contentmanager.ManagerConfiguration">
        <property name="nodeTypes" value="nt:file,nt:folder,jnt:mountPoint"/>
        <property name="folderTypes" value="nt:folder,jnt:mountPoint"/>
        <property name="toolbarSet">
            <bean class="org.jahia.services.uicomponents.bean.toolbar.ToolbarSet">
                <property name="toolbars">
                    <list>
                        <bean class="org.jahia.services.uicomponents.bean.toolbar.Toolbar">
                            <property name="items">
                                <list>
                                    <bean class="org.jahia.services.uicomponents.bean.toolbar.ItemsGroup">
                                        <property name="layout" value="menu"/>
                                        <property name="titleKey"
                                                  value="org.jahia.engines.filemanager.Filemanager_Engine.fileMenu.label"/>
                                        <property name="items">
                                            <list>
                                                <ref bean="org.jahia.toolbar.item.createFolder"/>
                                                <ref bean="org.jahia.toolbar.item.upload"/>
                                                <ref bean="org.jahia.toolbar.item.download"/>
                                                <ref bean="org.jahia.toolbar.item.preview"/>
                                                <ref bean="org.jahia.toolbar.item.Separator"/>
                                                <ref bean="org.jahia.toolbar.item.lock"/>
                                                <ref bean="org.jahia.toolbar.item.unlock"/>
                                                <ref bean="org.jahia.toolbar.item.Separator"/>
                                                <ref bean="org.jahia.toolbar.item.zip"/>
                                                <ref bean="org.jahia.toolbar.item.unzip"/>
                                            </list>
                                        </property>
                                    </bean>
                                    <ref bean="org.jahia.toolbar.itemsgroup.ContentManager.menu.edit"/>
                                    <ref bean="org.jahia.toolbar.itemsgroup.ContentManager.menu.remote"/>
                                    <ref bean="org.jahia.toolbar.itemsgroup.ContentManager.menu.image"/>
                                    <ref bean="org.jahia.toolbar.itemsgroup.ContentManager.menu.view"/>
                                </list>
                            </property>
                            <property name="contextMenu" value="true"/>
                            <property name="visibility">
                                <bean class="org.jahia.services.uicomponents.bean.Visibility">
                                    <property name="siteActionPermission" value="toolbar/documents-menu"/>
                                </bean>
                            </property>
                        </bean>
                        <ref bean="org.jahia.toolbar.manager.documents.shortcuts"/>
                    </list>
                </property>
            </bean>
        </property>
        <property name="enableTextMenu" value="true"/>
        <property name="displayProvider" value="true"/>
        <property name="displaySearchInPage" value="false"/>
        <property name="displaySearchInContent" value="false"/>
        <property name="displaySearchInFile" value="false"/>
        <property name="displaySearchInTag" value="true"/>
        <!-- accordion panels-->
        <property name="accordionPanels">
            <list>
                <ref bean="repository.website"/>
                <ref bean="repository.shared"/>
                <ref bean="repository.myexternal"/>
                <ref bean="repository.my"/>
                <ref bean="repository.users"/>
            </list>
        </property>
        <!-- tabs -->
        <property name="tabs">
            <list value-type="org.jahia.services.uicomponents.bean.editmode.EngineTab">
                <value>info</value>
                <value>rights</value>
                <value>usages</value>
                <value>classification</value>
                <value>versioning</value>
            </list>
        </property>
        <!-- table columns-->
        <property name="tableColumns">
            <list value-type="org.jahia.services.uicomponents.bean.contentmanager.Column">
                <bean class="org.jahia.services.uicomponents.bean.contentmanager.Column">
                    <property name="key" value="providerKey"/>
                    <property name="visibility">
                        <bean class="org.jahia.services.uicomponents.bean.contentmanager.ProviderKeyColumnVisibility">
                            <property name="jcrSessionFactory" ref="jcrSessionFactory"/>
                            <property name="alsoCountDynamicProviders" value="false"/>
                        </bean>
                    </property>
                </bean>
                <value>icon</value>
                <value>name</value>
                <value>locked</value>
                <value>path</value>
                <value>size</value>
                <value>lastModified</value>
            </list>
        </property>
    </bean>

    <!-- mashup manager -->
    <bean id="mashupmanager" class="org.jahia.services.uicomponents.bean.contentmanager.ManagerConfiguration">
        <property name="nodeTypes" value="jnt:portlet"/>
        <property name="folderTypes" value="jnt:portletList"/>
        <property name="toolbarSet">
            <bean class="org.jahia.services.uicomponents.bean.toolbar.ToolbarSet">
                <property name="toolbars">
                    <list>
                        <bean class="org.jahia.services.uicomponents.bean.toolbar.Toolbar">
                            <property name="items">
                                <list>
                                    <bean class="org.jahia.services.uicomponents.bean.toolbar.ItemsGroup">
                                        <property name="layout" value="menu"/>
                                        <property name="titleKey"
                                                  value="org.jahia.engines.filemanager.Filemanager_Engine.fileMenu.label"/>
                                        <property name="items">
                                            <list>
                                                <ref bean="org.jahia.toolbar.item.createFolder"/>
                                                <ref bean="org.jahia.toolbar.item.newMashup"/>
                                                <ref bean="org.jahia.toolbar.item.newRss"/>
                                                <ref bean="org.jahia.toolbar.item.newGadget"/>
                                            </list>
                                        </property>
                                    </bean>
                                    <ref bean="org.jahia.toolbar.itemsgroup.ContentManager.menu.edit"/>
                                    <ref bean="org.jahia.toolbar.itemsgroup.ContentManager.menu.view"/>
                                </list>
                            </property>
                            <property name="visibility">
                                <bean class="org.jahia.services.uicomponents.bean.Visibility">
                                    <property name="siteActionPermission" value="toolbar/mashups-menu"/>
                                </bean>
                            </property>
                        </bean>
                        <ref bean="org.jahia.toolbar.manager.mashups.shortcuts"/>
                    </list>
                </property>
            </bean>
        </property>
        <property name="enableTextMenu" value="true"/>
        <property name="enableFileDoubleClick" value="false"/>
        <property name="displayExt" value="false"/>
        <property name="displaySize" value="false"/>
        <property name="displaySearchInPage" value="false"/>
        <property name="displaySearchInContent" value="false"/>
        <property name="displaySearchInFile" value="false"/>
        <property name="displaySearchInTag" value="true"/>
        <property name="defaultView" value="3"/>

        <!-- accordion panels-->
        <property name="accordionPanels">
            <list>
                <ref bean="repository.websitemahsup"/>
                <ref bean="repository.shared"/>
                <ref bean="repository.mymashup"/>
            </list>
        </property>
        <!-- tabs -->
        <property name="tabs">
            <list value-type="org.jahia.services.uicomponents.bean.editmode.EngineTab">
                <value>info</value>
                <value>rights</value>
                <value>usages</value>
            </list>
        </property>
        <!-- table columns-->
        <property name="tableColumns">
            <list value-type="org.jahia.services.uicomponents.bean.contentmanager.Column">
                <value>name</value>
                <value>locked</value>
                <value>path</value>
                <value>lastModified</value>
            </list>
        </property>
    </bean>

    <!-- category manager -->
    <bean id="categorymanager" class="org.jahia.services.uicomponents.bean.contentmanager.ManagerConfiguration">
        <property name="nodeTypes" value="jnt:category"/>
        <property name="folderTypes" value="jnt:category"/>
        <property name="toolbarSet">
            <bean class="org.jahia.services.uicomponents.bean.toolbar.ToolbarSet">
                <property name="toolbars">
                    <list>
                        <bean class="org.jahia.services.uicomponents.bean.toolbar.Toolbar">
                            <property name="items">
                                <list>
                                    <bean class="org.jahia.services.uicomponents.bean.toolbar.ItemsGroup">
                                        <property name="layout" value="menu"/>
                                        <property name="titleKey"
                                                  value="org.jahia.engines.filemanager.Filemanager_Engine.fileMenu.label"/>
                                        <property name="items">
                                            <list>
                                                <ref bean="org.jahia.toolbar.item.newCategory"/>
                                                <ref bean="org.jahia.toolbar.item.Separator"/>
                                                <ref bean="org.jahia.toolbar.item.export"/>
                                                <ref bean="org.jahia.toolbar.item.import"/>
                                            </list>
                                        </property>
                                    </bean>
                                    <ref bean="org.jahia.toolbar.itemsgroup.ContentManager.menu.edit"/>
                                </list>
                            </property>
                            <property name="visibility">
                                <bean class="org.jahia.services.uicomponents.bean.Visibility">
                                    <property name="siteActionPermission" value="toolbar/categories-menu"/>
                                </bean>
                            </property>
                            <property name="contextMenu" value="true"/>
                        </bean>
                        <ref bean="org.jahia.toolbar.manager.categories.shortcuts"/>
                    </list>
                </property>
            </bean>
        </property>
        <property name="enableTextMenu" value="true"/>
        <property name="enableFileDoubleClick" value="false"/>
        <property name="displayExt" value="false"/>
        <property name="displaySize" value="false"/>
        <property name="displaySearchInPage" value="false"/>
        <property name="displaySearchInContent" value="false"/>
        <property name="displaySearchInFile" value="false"/>
        <property name="displaySearchInTag" value="true"/>
        <property name="defaultView" value="1"/>

        <!-- accordion panels-->
        <property name="accordionPanels">
            <list>
                <ref bean="repository.category"/>
            </list>
        </property>
        <!-- tabs -->
        <property name="tabs">
            <list value-type="org.jahia.services.uicomponents.bean.editmode.EngineTab">
                <value>info</value>
                <value>rights</value>
                <value>usages</value>
            </list>
        </property>
        <!-- table columns-->
        <property name="tableColumns">
            <list value-type="org.jahia.services.uicomponents.bean.contentmanager.Column">
                <value>icon</value>
                <value>name</value>
                <value>locked</value>
                <value>path</value>
            </list>
        </property>
    </bean>

    <!-- tag manager -->
    <bean id="tagmanager" class="org.jahia.services.uicomponents.bean.contentmanager.ManagerConfiguration">
        <property name="nodeTypes" value="jnt:tag"/>
        <property name="folderTypes" value="jnt:tag"/>
        <property name="toolbarSet">
            <bean class="org.jahia.services.uicomponents.bean.toolbar.ToolbarSet">
                <property name="toolbars">
                    <list>
                        <bean class="org.jahia.services.uicomponents.bean.toolbar.Toolbar">
                            <property name="items">
                                <list>
                                    <bean class="org.jahia.services.uicomponents.bean.toolbar.ItemsGroup">
                                        <property name="layout" value="button"/>
                                        <property name="items">
                                            <list>
                                                <ref bean="org.jahia.toolbar.item.newTag"/>
                                                <ref bean="org.jahia.toolbar.item.Separator"/>
                                                <ref bean="org.jahia.toolbar.item.export"/>
                                                <ref bean="org.jahia.toolbar.item.import"/>
                                            </list>
                                        </property>
                                    </bean>
                                    <ref bean="org.jahia.toolbar.itemsgroup.ContentManager.shortcuts.file.modify"/>
                                    <ref bean="org.jahia.toolbar.itemsgroup.ContentManager.shortcuts.copy"/>
                                    <ref bean="org.jahia.toolbar.itemsgroup.ContentManager.shortcuts.refresh"/>
                                </list>
                            </property>
                            <property name="visibility">
                                <bean class="org.jahia.services.uicomponents.bean.Visibility">
                                    <property name="siteActionPermission" value="toolbar/tags-shortcuts"/>
                                </bean>
                            </property>
                        </bean>
                        <bean class="org.jahia.services.uicomponents.bean.toolbar.Toolbar">
                            <property name="items">
                                <list>
                                    <bean class="org.jahia.services.uicomponents.bean.toolbar.ItemsGroup">
                                        <property name="layout" value="menu"/>
                                        <property name="titleKey"
                                                  value="org.jahia.engines.filemanager.Filemanager_Engine.fileMenu.label"/>
                                        <property name="items">
                                            <list>
                                                <ref bean="org.jahia.toolbar.item.newTag"/>
                                                <ref bean="org.jahia.toolbar.item.Separator"/>
                                                <ref bean="org.jahia.toolbar.item.export"/>
                                                <ref bean="org.jahia.toolbar.item.import"/>
                                            </list>
                                        </property>
                                    </bean>
                                    <ref bean="org.jahia.toolbar.itemsgroup.ContentManager.menu.edit"/>
                                </list>
                            </property>
                            <property name="visibility">
                                <bean class="org.jahia.services.uicomponents.bean.Visibility">
                                    <property name="siteActionPermission" value="toolbar/tags-menu"/>
                                </bean>
                            </property>
                            <property name="contextMenu" value="true"/>
                        </bean>
                    </list>
                </property>
            </bean>
        </property>
        <property name="hideLeftPanel" value="true"/>
        <property name="enableTextMenu" value="true"/>
        <property name="displayExt" value="false"/>
        <property name="displaySize" value="false"/>
        <property name="displayDate" value="false"/>
        <property name="displaySearch" value="false"/>
        <property name="expandRoot" value="true"/>
        <property name="displaySearchInPage" value="false"/>
        <property name="displaySearchInContent" value="false"/>
        <property name="displaySearchInFile" value="false"/>
        <property name="displaySearchInTag" value="false"/>
        <property name="defaultView" value="1"/>

        <!-- accordion panels-->
        <property name="accordionPanels">
            <list>
                <ref bean="repository.tag"/>
            </list>
        </property>
        <!-- tabs -->
        <property name="tabs">
            <list value-type="org.jahia.services.uicomponents.bean.editmode.EngineTab">
                <value>rights</value>
                <value>usages</value>
            </list>
        </property>
        <!-- table columns-->
        <property name="tableColumns">
            <list value-type="org.jahia.services.uicomponents.bean.contentmanager.Column">
                <value>icon</value>
                <value>name</value>
                <value>count</value>
                <value>locked</value>
                <value>path</value>
            </list>
        </property>

    </bean>

    <!-- remote publication manager -->
    <bean id="remotepublicationmanager"
          class="org.jahia.services.uicomponents.bean.contentmanager.ManagerConfiguration">
        <property name="nodeTypes" value="jnt:remotePublication"/>
        <property name="folderTypes" value="jnt:remotePublications"/>
        <property name="toolbarSet">
            <bean class="org.jahia.services.uicomponents.bean.toolbar.ToolbarSet">
                <property name="toolbars">
                    <list>
                        <bean class="org.jahia.services.uicomponents.bean.toolbar.Toolbar">
                            <property name="items">
                                <list>
                                    <bean class="org.jahia.services.uicomponents.bean.toolbar.ItemsGroup">
                                        <property name="layout" value="button"/>
                                        <property name="items">
                                            <list>
                                                <ref bean="org.jahia.toolbar.item.exectuteRemotePublication"/>
                                                <ref bean="org.jahia.toolbar.item.newRemotePublication"/>
                                            </list>
                                        </property>
                                    </bean>
                                </list>
                            </property>
                            <property name="visibility">
                                <bean class="org.jahia.services.uicomponents.bean.Visibility">
                                    <property name="siteActionPermission" value="toolbar/remotepublication-shortcuts"/>
                                </bean>
                            </property>
                        </bean>
                        <bean class="org.jahia.services.uicomponents.bean.toolbar.Toolbar">
                            <property name="items">
                                <list>
                                    <bean class="org.jahia.services.uicomponents.bean.toolbar.ItemsGroup">
                                        <property name="layout" value="menu"/>
                                        <property name="titleKey"
                                                  value="org.jahia.engines.filemanager.Filemanager_Engine.fileMenu.label"/>
                                        <property name="items">
                                            <list>
                                                <ref bean="org.jahia.toolbar.item.newRemotePublication"/>
                                            </list>
                                        </property>
                                    </bean>
                                </list>
                            </property>
                            <property name="visibility">
                                <bean class="org.jahia.services.uicomponents.bean.Visibility">
                                    <property name="siteActionPermission" value="toolbar/remotepublication-menu"/>
                                </bean>
                            </property>
                            <property name="contextMenu" value="true"/>
                        </bean>
                    </list>
                </property>
            </bean>
        </property>
        <property name="hideLeftPanel" value="true"/>
        <property name="enableTextMenu" value="true"/>
        <property name="displayExt" value="false"/>
        <property name="displaySize" value="false"/>
        <property name="displayDate" value="false"/>
        <property name="displaySearch" value="false"/>
        <property name="expandRoot" value="true"/>
        <property name="displaySearchInPage" value="false"/>
        <property name="displaySearchInContent" value="false"/>
        <property name="displaySearchInFile" value="false"/>
        <property name="displaySearchInTag" value="false"/>
        <property name="defaultView" value="1"/>

        <!-- accordion panels-->
        <property name="accordionPanels">
            <list>
                <ref bean="repository.remotePublication"/>
            </list>
        </property>
        <!-- tabs -->
        <property name="tabs">
            <list value-type="org.jahia.services.uicomponents.bean.editmode.EngineTab">
                <value>rights</value>
            </list>
        </property>
        <!-- table columns-->
        <property name="tableColumns">
            <list value-type="org.jahia.services.uicomponents.bean.contentmanager.Column">
                <value>name</value>
            </list>
        </property>

    </bean>


    <!-- portlet definition manager -->
    <bean id="portletdefinitionmanager"
          class="org.jahia.services.uicomponents.bean.contentmanager.ManagerConfiguration">

        <property name="nodeTypes" value="jnt:portletDefinitions"/>
        <property name="folderTypes" value="nt:folder"/>
        <property name="toolbarSet">
            <bean class="org.jahia.services.uicomponents.bean.toolbar.ToolbarSet">
                <property name="toolbars">
                    <list>
                        <bean class="org.jahia.services.uicomponents.bean.toolbar.Toolbar">
                            <property name="items">
                                <list>
                                    <bean class="org.jahia.services.uicomponents.bean.toolbar.ItemsGroup">
                                        <property name="layout" value="button"/>
                                        <property name="items">
                                            <list>
                                                <ref bean="org.jahia.toolbar.item.delete"/>
                                            </list>
                                        </property>
                                    </bean>
                                    <ref bean="org.jahia.toolbar.itemsgroup.ContentManager.shortcuts.refresh"/>
                                </list>
                            </property>
                            <property name="visibility">
                                <bean class="org.jahia.services.uicomponents.bean.Visibility">
                                    <property name="siteActionPermission" value="toolbar/portletDefinitions-shortcuts"/>
                                </bean>
                            </property>
                        </bean>
                    </list>
                </property>
            </bean>
        </property>
        <property name="hideLeftPanel" value="true"/>
        <property name="enableTextMenu" value="false"/>
        <property name="enableFileDoubleClick" value="false"/>
        <property name="displayExt" value="false"/>
        <property name="displaySize" value="false"/>
        <property name="displayDate" value="false"/>
        <property name="expandRoot" value="true"/>
        <property name="displaySearchInPage" value="false"/>
        <property name="displaySearchInContent" value="false"/>
        <property name="displaySearchInFile" value="false"/>
        <property name="displaySearchInTag" value="true"/>
        <property name="defaultView" value="1"/>

        <!-- accordion panels-->
        <property name="accordionPanels">
            <list>
                <ref bean="repository.portletdefinition"/>
            </list>
        </property>
        <!-- tabs -->
        <property name="tabs">
            <list value-type="org.jahia.services.uicomponents.bean.editmode.EngineTab">
                <value>portlets</value>
                <value>rights</value>
                <value>usages</value>
            </list>
        </property>
        <!-- table columns-->
        <property name="tableColumns">
            <list value-type="org.jahia.services.uicomponents.bean.contentmanager.Column">
                <value>name</value>
            </list>
        </property>

    </bean>


    <!-- file manager -->
    <bean id="contentmanager" class="org.jahia.services.uicomponents.bean.contentmanager.ManagerConfiguration">
        <property name="nodeTypes" value="nt:base"/>
        <property name="folderTypes" value="nt:base"/>
        <property name="enableTextMenu" value="true"/>
        <property name="toolbarSet">
            <bean class="org.jahia.services.uicomponents.bean.toolbar.ToolbarSet">
                <property name="toolbars">
                    <list>
                        <bean class="org.jahia.services.uicomponents.bean.toolbar.Toolbar">
                            <property name="items">
                                <list>
                                    <bean class="org.jahia.services.uicomponents.bean.toolbar.ItemsGroup">
                                        <property name="layout" value="menu"/>
                                        <property name="titleKey"
                                                  value="org.jahia.engines.filemanager.Filemanager_Engine.fileMenu.label"/>
                                        <property name="items">
                                            <list>
                                                <ref bean="org.jahia.toolbar.item.createFolder"/>
                                                <ref bean="org.jahia.toolbar.item.newContentList"/>
                                                <ref bean="org.jahia.toolbar.item.createContent"/>
                                                <ref bean="org.jahia.toolbar.item.createPage"/>
                                                <ref bean="org.jahia.toolbar.item.newMashup"/>
                                                <ref bean="org.jahia.toolbar.item.newRss"/>
                                                <ref bean="org.jahia.toolbar.item.newGadget"/>
                                                <ref bean="org.jahia.toolbar.item.upload"/>
                                                <ref bean="org.jahia.toolbar.item.download"/>
                                                <ref bean="org.jahia.toolbar.item.Separator"/>
                                                <ref bean="org.jahia.toolbar.item.lock"/>
                                                <ref bean="org.jahia.toolbar.item.unlock"/>
                                                <ref bean="org.jahia.toolbar.item.Separator"/>
                                                <ref bean="org.jahia.toolbar.item.zip"/>
                                                <ref bean="org.jahia.toolbar.item.unzip"/>
                                                <ref bean="org.jahia.toolbar.item.Separator"/>
                                                <ref bean="org.jahia.toolbar.item.export"/>
                                                <ref bean="org.jahia.toolbar.item.import"/>
                                            </list>
                                        </property>
                                    </bean>
                                    <ref bean="org.jahia.toolbar.itemsgroup.ContentManager.menu.edit"/>
                                    <ref bean="org.jahia.toolbar.itemsgroup.ContentManager.menu.remote"/>
                                    <ref bean="org.jahia.toolbar.itemsgroup.ContentManager.menu.image"/>
                                    <ref bean="org.jahia.toolbar.itemsgroup.ContentManager.menu.view"/>
                                </list>
                            </property>
                            <property name="contextMenu" value="true"/>
                            <property name="visibility">
                                <bean class="org.jahia.services.uicomponents.bean.Visibility">
                                    <property name="siteActionPermission" value="toolbar/content-menu"/>
                                </bean>
                            </property>
                        </bean>
                        <ref bean="org.jahia.toolbar.manager.content.shortcuts"/>
                    </list>
                </property>
            </bean>
        </property>
        <property name="displaySearchInPage" value="false"/>
        <property name="displaySearchInContent" value="true"/>
        <property name="displaySearchInFile" value="true"/>
        <property name="displaySearchInTag" value="true"/>
        <!-- accordion -->
        <property name="accordionPanels">
            <list>
                <ref bean="repository.global"/>
            </list>
        </property>

        <!-- table columns-->
        <property name="tableColumns">
            <list value-type="org.jahia.services.uicomponents.bean.contentmanager.Column">
                <bean class="org.jahia.services.uicomponents.bean.contentmanager.Column">
                    <property name="key" value="providerKey"/>
                    <property name="visibility">
                        <bean class="org.jahia.services.uicomponents.bean.contentmanager.ProviderKeyColumnVisibility">
                            <property name="jcrSessionFactory" ref="jcrSessionFactory"/>
                            <property name="alsoCountDynamicProviders" value="false"/>
                        </bean>
                    </property>
                </bean>
                <value>icon</value>
                <value>name</value>
                <value>locked</value>
                <value>path</value>
                <value>size</value>
                <value>publicationInfo</value>
                <value>created</value>
                <value>createdBy</value>
                <value>lastModified</value>
                <value>lastModifiedBy</value>
                <value>lastPublished</value>
                <value>lastPublishedBy</value>
            </list>
        </property>

        <!-- tabs -->
        <property name="tabs">
            <list value-type="org.jahia.services.uicomponents.bean.editmode.EngineTab">
                <value>info</value>
                <value>content</value>
                <value>layout</value>
                <value>metadata</value>
                <value>classification</value>
                <value>option</value>
                <value>rights</value>
                <value>usages</value>
                <value>publication</value>
                <value>workflow</value>
                <value>seo</value>
                <value>analytics</value>
            </list>
        </property>


    </bean>

    <!-- sitemanager manager -->
    <bean id="sitemanager" class="org.jahia.services.uicomponents.bean.contentmanager.ManagerConfiguration">
        <property name="nodeTypes" value="jnt:page"/>
        <property name="folderTypes" value="jnt:page"/>
        <property name="enableTextMenu" value="true"/>
        <property name="displaySize" value="false"/>
        <property name="displayDate" value="false"/>
        <property name="allowCollections" value="true"/>
        <property name="toolbarSet">
            <bean class="org.jahia.services.uicomponents.bean.toolbar.ToolbarSet">
                <property name="toolbars">
                    <list>
                        <bean class="org.jahia.services.uicomponents.bean.toolbar.Toolbar">
                            <property name="items">
                                <list>
                                    <bean class="org.jahia.services.uicomponents.bean.toolbar.ItemsGroup">
                                        <property name="layout" value="button"/>
                                        <property name="items">
                                            <list>
                                                <ref bean="org.jahia.toolbar.item.createPage"/>
                                            </list>
                                        </property>
                                    </bean>
                                    <ref bean="org.jahia.toolbar.itemsgroup.ContentManager.shortcuts.file.modify"/>
                                    <ref bean="org.jahia.toolbar.itemsgroup.ContentManager.shortcuts.copy"/>
                                    <ref bean="org.jahia.toolbar.itemsgroup.ContentManager.shortcuts.refresh"/>
                                </list>
                            </property>
                            <property name="visibility">
                                <bean class="org.jahia.services.uicomponents.bean.Visibility">
                                    <property name="siteActionPermission" value="toolbar/sites-shortcuts"/>
                                </bean>
                            </property>
                        </bean>
                        <bean class="org.jahia.services.uicomponents.bean.toolbar.Toolbar">
                            <property name="items">
                                <list>
                                    <bean class="org.jahia.services.uicomponents.bean.toolbar.ItemsGroup">
                                        <property name="layout" value="menu"/>
                                        <property name="titleKey"
                                                  value="org.jahia.engines.filemanager.Filemanager_Engine.fileMenu.label"/>
                                        <property name="items">
                                            <list>
                                                <ref bean="org.jahia.toolbar.item.createPage"/>
                                                <ref bean="org.jahia.toolbar.item.Separator"/>
                                                <ref bean="org.jahia.toolbar.item.lock"/>
                                                <ref bean="org.jahia.toolbar.item.unlock"/>
                                            </list>
                                        </property>
                                    </bean>
                                    <ref bean="org.jahia.toolbar.itemsgroup.ContentManager.menu.edit"/>
                                </list>
                            </property>
                            <property name="contextMenu" value="true"/>
                            <property name="visibility">
                                <bean class="org.jahia.services.uicomponents.bean.Visibility">
                                    <property name="siteActionPermission" value="toolbar/sites-menu"/>
                                </bean>
                            </property>
                        </bean>
                    </list>
                </property>
            </bean>
        </property>
        <property name="displaySearchInPage" value="true"/>
        <property name="displaySearchInContent" value="false"/>
        <property name="displaySearchInFile" value="false"/>
        <property name="displaySearchInTag" value="true"/>
        <property name="defaultView" value="1"/>


        <!-- accordion -->
        <property name="accordionPanels">
            <list>
                <ref bean="repository.site"/>
            </list>
        </property>

        <!-- columns -->
        <property name="tableColumns">
            <list value-type="org.jahia.services.uicomponents.bean.contentmanager.Column">
                <value>icon</value>
                <value>name</value>
                <value>locked</value>
                <value>lastModified</value>
                <value>lastModifiedBy</value>
                <value>publicationInfo</value>
            </list>
        </property>

        <!-- tabs -->
        <property name="tabs">
            <list value-type="org.jahia.services.uicomponents.bean.editmode.EngineTab">
                <value>info</value>
                <value>rights</value>
                <value>usages</value>
                <value>versioning</value>
                <value>analytics</value>
                <value>seo</value>
            </list>
        </property>
    </bean>

    <!-- file manager -->
    <bean id="rolesmanager" class="org.jahia.services.uicomponents.bean.contentmanager.ManagerConfiguration">
        <property name="nodeTypes" value="jnt:role"/>
        <property name="folderTypes" value="jnt:role"/>
        <property name="toolbarSet">
            <bean class="org.jahia.services.uicomponents.bean.toolbar.ToolbarSet">
                <property name="toolbars">
                    <list>
                        <ref bean="org.jahia.toolbar.manager.roles.menu"/>
                        <ref bean="org.jahia.toolbar.manager.roles.shortcuts"/>
                    </list>
                </property>
            </bean>
        </property>

        <property name="hideLeftPanel" value="true"/>
        <property name="enableTextMenu" value="true"/>
        <property name="displayExt" value="false"/>
        <property name="displaySize" value="false"/>
        <property name="displayDate" value="false"/>
        <property name="displaySearch" value="false"/>
        <property name="expandRoot" value="true"/>
        <property name="displaySearchInPage" value="false"/>
        <property name="displaySearchInContent" value="false"/>
        <property name="displaySearchInFile" value="false"/>
        <property name="displaySearchInTag" value="false"/>
        <property name="defaultView" value="1"/>

        <!-- accordion panels-->
        <property name="accordionPanels">
            <list>
                <ref bean="repository.role"/>
            </list>
        </property>
        <!-- tabs -->
        <property name="tabs">
            <list value-type="org.jahia.services.uicomponents.bean.editmode.EngineTab">
                <value>principalRolesMapping</value>
            </list>
        </property>
        <!-- table columns-->
        <property name="tableColumns">
            <list value-type="org.jahia.services.uicomponents.bean.contentmanager.Column">
                <value>name</value>
            </list>
        </property>
    </bean>


    <!-- file manager -->
    <bean id="siterolesmanager" class="org.jahia.services.uicomponents.bean.contentmanager.ManagerConfiguration">
        <property name="nodeTypes" value="jnt:role"/>
        <property name="folderTypes" value="jnt:role"/>
        <property name="toolbarSet">
            <bean class="org.jahia.services.uicomponents.bean.toolbar.ToolbarSet">
                <property name="toolbars">
                    <list>
                        <ref bean="org.jahia.toolbar.manager.roles.menu"/>
                        <ref bean="org.jahia.toolbar.manager.roles.shortcuts"/>
                    </list>
                </property>
            </bean>
        </property>

        <property name="hideLeftPanel" value="true"/>
        <property name="enableTextMenu" value="true"/>
        <property name="displayExt" value="false"/>
        <property name="displaySize" value="false"/>
        <property name="displayDate" value="false"/>
        <property name="displaySearch" value="false"/>
        <property name="expandRoot" value="true"/>
        <property name="displaySearchInPage" value="false"/>
        <property name="displaySearchInContent" value="false"/>
        <property name="displaySearchInFile" value="false"/>
        <property name="displaySearchInTag" value="true"/>
        <property name="defaultView" value="1"/>

        <!-- accordion panels-->
        <property name="accordionPanels">
            <list>
                <ref bean="repository.siteRole"/>
            </list>
        </property>
        <!-- tabs -->
        <property name="tabs">
            <list value-type="org.jahia.services.uicomponents.bean.editmode.EngineTab">
                <value>principalRolesMapping</value>
            </list>
        </property>
        <!-- table columns-->
        <property name="tableColumns">
            <list value-type="org.jahia.services.uicomponents.bean.contentmanager.Column">
                <value>name</value>
            </list>
        </property>

    </bean>

    <!-- filepicker -->
    <bean id="filepicker" class="org.jahia.services.uicomponents.bean.contentmanager.ManagerConfiguration">
        <property name="nodeTypes" value="nt:file,nt:folder,jnt:mountPoint"/>
        <property name="folderTypes" value="nt:folder,jnt:mountPoint"/>
        <property name="enableTextMenu" value="false"/>
        <property name="toolbarSet">
            <bean class="org.jahia.services.uicomponents.bean.toolbar.ToolbarSet">
                <property name="toolbars">
                    <list>
                        <ref bean="org.jahia.toolbar.manager.documents.shortcuts"/>
                    </list>
                </property>
            </bean>
        </property>
        <property name="hideLeftPanel" value="true"/>
        <property name="displaySearchInPage" value="false"/>
        <property name="displaySearchInContent" value="false"/>
        <property name="displaySearchInFile" value="false"/>
        <property name="displaySearchInTag" value="true"/>

        <property name="tabs">
            <list value-type="org.jahia.services.uicomponents.bean.editmode.EngineTab">
                <value>info</value>
                <value>rights</value>
                <value>usages</value>
                <value>versioning</value>
            </list>
        </property>
        <!-- accordion panels-->
        <property name="accordionPanels">
            <list>
                <ref bean="repository.website"/>
                <ref bean="repository.shared"/>
                <ref bean="repository.myexternal"/>
                <ref bean="repository.users"/>
            </list>
        </property>

    </bean>

    <!-- content picker -->
    <bean id="contentpicker" class="org.jahia.services.uicomponents.bean.contentmanager.ManagerConfiguration">
        <property name="nodeTypes" value="nt:base"/>
        <property name="folderTypes" value="nt:base"/>
        <property name="enableTextMenu" value="false"/>
        <property name="toolbarSet">
            <bean class="org.jahia.services.uicomponents.bean.toolbar.ToolbarSet">
                <property name="toolbars">
                    <list>
                        <ref bean="org.jahia.toolbar.manager.content.shortcuts"/>
                    </list>
                </property>
            </bean>
        </property>
        <property name="hideLeftPanel" value="true"/>

        <property name="displaySearchInPage" value="true"/>
        <property name="displaySearchInContent" value="true"/>
        <property name="displaySearchInTag" value="true"/>

        <!-- tabs -->
        <property name="tabs">
            <list value-type="org.jahia.services.uicomponents.bean.editmode.EngineTab">
                <value>info</value>
                <value>rights</value>
                <value>usages</value>
                <value>versioning</value>
            </list>
        </property>

        <!-- accordion panels-->
        <property name="accordionPanels">
            <list>
                <ref bean="repository.global"/>
                <ref bean="repository.website"/>
                <ref bean="repository.shared"/>
                <ref bean="repository.myexternal"/>
                <ref bean="repository.my"/>
            </list>
        </property>

    </bean>

    <!-- file manager -->
    <bean id="linkpicker" class="org.jahia.services.uicomponents.bean.contentmanager.ManagerConfiguration">
        <property name="nodeTypes" value="jnt:page"/>
        <property name="folderTypes" value="nt:folder"/>
        <property name="toolbarSet">
            <bean class="org.jahia.services.uicomponents.bean.toolbar.ToolbarSet">
                <property name="toolbars">
                    <list>
                        <ref bean="org.jahia.toolbar.manager.documents.shortcuts"/>
                    </list>
                </property>
            </bean>
        </property>
        <property name="enableTextMenu" value="false"/>
        <property name="hideLeftPanel" value="true"/>
        <property name="displaySearchInPage" value="false"/>
        <property name="displaySearchInContent" value="false"/>
        <property name="displaySearchInFile" value="false"/>
        <property name="displaySearchInTag" value="true"/>
        <!-- accordion panels-->
        <property name="accordionPanels">
            <list>
                <ref bean="repository.website"/>
            </list>
        </property>

        <!-- tabs -->
        <property name="tabs">
            <list value-type="org.jahia.services.uicomponents.bean.editmode.EngineTab">
                <value>info</value>
                <value>rights</value>
                <value>usages</value>
                <value>versioning</value>
            </list>
        </property>


    </bean>

    <!-- file manager -->
    <bean id="mashuppicker" class="org.jahia.services.uicomponents.bean.contentmanager.ManagerConfiguration">
        <property name="nodeTypes" value="jnt:portlet"/>
        <property name="folderTypes" value="jnt:portletList"/>
        <property name="toolbarSet">
            <bean class="org.jahia.services.uicomponents.bean.toolbar.ToolbarSet">
                <property name="toolbars">
                    <list>
                        <ref bean="org.jahia.toolbar.manager.mashups.shortcuts"/>
                    </list>
                </property>
            </bean>
        </property>
        <property name="displaySearchInPage" value="false"/>
        <property name="displaySearchInContent" value="false"/>
        <property name="displaySearchInFile" value="false"/>
        <property name="displaySearchInTag" value="true"/>
        <property name="enableTextMenu" value="false"/>
        <property name="enableFileDoubleClick" value="false"/>
        <property name="displayExt" value="false"/>
        <property name="displaySize" value="false"/>
        <property name="hideLeftPanel" value="true"/>

        <property name="tableColumns">
            <list value-type="org.jahia.services.uicomponents.bean.contentmanager.Column">
                <value>name</value>
                <value>picker</value>
            </list>
        </property>

        <property name="defaultView" value="3"/>

        <!-- accordion panels-->
        <property name="accordionPanels">
            <list>
                <ref bean="repository.websitemahsup"/>
                <ref bean="repository.sharedmashup"/>
                <ref bean="repository.mymashup"/>
            </list>
        </property>

        <!-- tabs -->
        <property name="tabs">
            <list value-type="org.jahia.services.uicomponents.bean.editmode.EngineTab">
                <value>info</value>
                <value>rights</value>
                <value>usages</value>
            </list>
        </property>

    </bean>

    <!-- categorypicker -->
    <bean id="categorypicker" class="org.jahia.services.uicomponents.bean.contentmanager.ManagerConfiguration">
        <property name="nodeTypes" value="jnt:category"/>
        <property name="folderTypes" value="jnt:category"/>
        <property name="enableTextMenu" value="false"/>
        <property name="enableFileDoubleClick" value="false"/>
        <property name="displayExt" value="false"/>
        <property name="displaySize" value="false"/>
        <property name="toolbarSet">
            <bean class="org.jahia.services.uicomponents.bean.toolbar.ToolbarSet">
                <property name="toolbars">
                    <list>
                        <ref bean="org.jahia.toolbar.manager.categories.shortcuts"/>
                    </list>
                </property>
            </bean>
        </property>
        <property name="displaySearchInPage" value="false"/>
        <property name="displaySearchInContent" value="false"/>
        <property name="displaySearchInFile" value="false"/>
        <property name="displaySearchInTag" value="true"/>
        <property name="hideLeftPanel" value="true"/>
        <property name="defaultView" value="3"/>

        <!-- columns -->
        <property name="tableColumns">
            <list value-type="org.jahia.services.uicomponents.bean.contentmanager.Column">
                <value>name</value>
                <value>picker</value>
            </list>
        </property>

        <!-- accordion -->
        <property name="accordionPanels">
            <list>
                <ref bean="repository.category"/>
            </list>
        </property>

        <!-- tabs -->
        <property name="tabs">
            <list value-type="org.jahia.services.uicomponents.bean.editmode.EngineTab">
                <value>info</value>
                <value>rights</value>
                <value>usages</value>
            </list>
        </property>


    </bean>


    <!-- Category Manager -->
    <bean id="org.jahia.toolbar.manager.categories.shortcuts"
          class="org.jahia.services.uicomponents.bean.toolbar.Toolbar">
        <property name="items">
            <list>
                <bean class="org.jahia.services.uicomponents.bean.toolbar.ItemsGroup">
                    <property name="layout" value="button"/>
                    <property name="items">
                        <list>
                            <ref bean="org.jahia.toolbar.item.newCategory"/>
                            <ref bean="org.jahia.toolbar.item.Separator"/>
                            <ref bean="org.jahia.toolbar.item.export"/>
                            <ref bean="org.jahia.toolbar.item.import"/>
                        </list>
                    </property>
                </bean>
                <ref bean="org.jahia.toolbar.itemsgroup.ContentManager.shortcuts.file.modify"/>
                <ref bean="org.jahia.toolbar.itemsgroup.ContentManager.shortcuts.copy"/>
                <ref bean="org.jahia.toolbar.itemsgroup.ContentManager.shortcuts.refresh"/>
            </list>
        </property>
        <property name="visibility">
            <bean class="org.jahia.services.uicomponents.bean.Visibility">
                <property name="siteActionPermission" value="toolbar/categories-shortcuts"/>
            </bean>
        </property>
    </bean>
    <!-- end of the Category Manager -->

    <!-- Content Manager -->
    <bean id="org.jahia.toolbar.manager.content.shortcuts" class="org.jahia.services.uicomponents.bean.toolbar.Toolbar">
        <property name="items">
            <list>
                <bean class="org.jahia.services.uicomponents.bean.toolbar.ItemsGroup">
                    <property name="layout" value="button"/>
                    <property name="items">
                        <list>
                            <ref bean="org.jahia.toolbar.item.createFolder"/>
                            <ref bean="org.jahia.toolbar.item.newContentList"/>
                            <ref bean="org.jahia.toolbar.item.createContent"/>
                            <ref bean="org.jahia.toolbar.item.createPage"/>
                            <ref bean="org.jahia.toolbar.item.newMashup"/>
                            <ref bean="org.jahia.toolbar.item.newRss"/>
                            <ref bean="org.jahia.toolbar.item.newGadget"/>
                            <ref bean="org.jahia.toolbar.item.upload"/>
                            <ref bean="org.jahia.toolbar.item.download"/>
                            <ref bean="org.jahia.toolbar.item.webfolder"/>
                        </list>
                    </property>
                </bean>
                <ref bean="org.jahia.toolbar.itemsgroup.ContentManager.shortcuts.file.modify"/>
                <ref bean="org.jahia.toolbar.itemsgroup.ContentManager.shortcuts.copy"/>
                <ref bean="org.jahia.toolbar.itemsgroup.ContentManager.shortcuts.refresh"/>
            </list>
        </property>
        <property name="visibility">
            <bean class="org.jahia.services.uicomponents.bean.Visibility">
                <property name="siteActionPermission" value="toolbar/content-shortcuts"/>
            </bean>
        </property>
    </bean>
    <!-- end of the Content Manager -->

    <!-- Document Manager -->

    <bean id="org.jahia.toolbar.manager.documents.shortcuts"
          class="org.jahia.services.uicomponents.bean.toolbar.Toolbar">
        <property name="items">
            <list>
                <bean class="org.jahia.services.uicomponents.bean.toolbar.ItemsGroup">
                    <property name="layout" value="button"/>
                    <property name="items">
                        <list>
                            <ref bean="org.jahia.toolbar.item.createFolder"/>
                            <ref bean="org.jahia.toolbar.item.upload"/>
                            <ref bean="org.jahia.toolbar.item.download"/>
                            <ref bean="org.jahia.toolbar.item.preview"/>
                            <ref bean="org.jahia.toolbar.item.webfolder"/>
                        </list>
                    </property>
                </bean>
                <ref bean="org.jahia.toolbar.itemsgroup.ContentManager.shortcuts.file.modify"/>
                <ref bean="org.jahia.toolbar.itemsgroup.ContentManager.shortcuts.copy"/>
                <ref bean="org.jahia.toolbar.itemsgroup.ContentManager.shortcuts.refresh"/>
            </list>
        </property>
        <property name="visibility">
            <bean class="org.jahia.services.uicomponents.bean.Visibility">
                <property name="siteActionPermission" value="toolbar/documents-shortcuts"/>
            </bean>
        </property>
    </bean>
    <!-- end of the Document Manager -->

    <!-- Mashup Manager -->
    <bean id="org.jahia.toolbar.manager.mashups.shortcuts" class="org.jahia.services.uicomponents.bean.toolbar.Toolbar">
        <property name="contextMenu" value="true"/>
        <property name="items">
            <list>
                <bean class="org.jahia.services.uicomponents.bean.toolbar.ItemsGroup">
                    <property name="layout" value="button"/>
                    <property name="items">
                        <list>
                            <ref bean="org.jahia.toolbar.item.createFolder"/>
                            <ref bean="org.jahia.toolbar.item.newMashup"/>
                            <ref bean="org.jahia.toolbar.item.newRss"/>
                            <ref bean="org.jahia.toolbar.item.newGadget"/>
                        </list>
                    </property>
                </bean>
                <ref bean="org.jahia.toolbar.itemsgroup.ContentManager.shortcuts.file.modify"/>
                <ref bean="org.jahia.toolbar.itemsgroup.ContentManager.shortcuts.copy"/>
                <ref bean="org.jahia.toolbar.itemsgroup.ContentManager.shortcuts.refresh"/>
            </list>
        </property>
        <property name="visibility">
            <bean class="org.jahia.services.uicomponents.bean.Visibility">
                <property name="siteActionPermission" value="toolbar/mashups-shortcuts"/>
            </bean>
        </property>
    </bean>
    <!-- end of the Mashup Manager -->

    <!-- roles -->
    <bean id="org.jahia.toolbar.manager.roles.menu" class="org.jahia.services.uicomponents.bean.toolbar.Toolbar">
        <property name="items">
            <list>
                <bean class="org.jahia.services.uicomponents.bean.toolbar.ItemsGroup">
                    <property name="layout" value="menu"/>
                    <property name="titleKey" value="org.jahia.engines.filemanager.Filemanager_Engine.fileMenu.label"/>
                    <property name="items">
                        <list>
                            <ref bean="org.jahia.toolbar.item.newRole"/>
                            <ref bean="org.jahia.toolbar.item.Separator"/>
                            <ref bean="org.jahia.toolbar.item.export"/>
                            <ref bean="org.jahia.toolbar.item.import"/>
                        </list>
                    </property>
                </bean>
                <bean class="org.jahia.services.uicomponents.bean.toolbar.ItemsGroup">
                    <property name="layout" value="menu"/>
                    <property name="titleKey" value="label.edit"/>
                    <property name="items">
                        <list>
                            <ref bean="org.jahia.toolbar.item.rename"/>
                            <ref bean="org.jahia.toolbar.item.delete"/>
                        </list>
                    </property>
                </bean>
            </list>
        </property>
        <property name="visibility">
            <bean class="org.jahia.services.uicomponents.bean.Visibility">
                <property name="siteActionPermission" value="toolbar/roles-menu"/>
            </bean>
        </property>
        <property name="contextMenu" value="true"/>
    </bean>
    <bean id="org.jahia.toolbar.manager.roles.shortcuts" class="org.jahia.services.uicomponents.bean.toolbar.Toolbar">
        <property name="items">
            <list>
                <bean class="org.jahia.services.uicomponents.bean.toolbar.ItemsGroup">
                    <property name="layout" value="button"/>
                    <property name="items">
                        <list>
                            <ref bean="org.jahia.toolbar.item.newRole"/>
                            <ref bean="org.jahia.toolbar.item.Separator"/>
                            <ref bean="org.jahia.toolbar.item.export"/>
                            <ref bean="org.jahia.toolbar.item.import"/>
                        </list>
                    </property>
                </bean>
                <ref bean="org.jahia.toolbar.itemsgroup.ContentManager.shortcuts.file.modify"/>
                <ref bean="org.jahia.toolbar.itemsgroup.ContentManager.shortcuts.refresh"/>
            </list>
        </property>
        <property name="visibility">
            <bean class="org.jahia.services.uicomponents.bean.Visibility">
                <property name="siteActionPermission" value="toolbar/roles-shortcuts"/>
            </bean>
        </property>
    </bean>


    <!-- accordion -->
    <bean id="repository.global" class="org.jahia.services.uicomponents.bean.contentmanager.Repository">
        <property name="key" value="globalRepository"/>
    </bean>

    <bean id="repository.website" class="org.jahia.services.uicomponents.bean.contentmanager.Repository">
        <property name="key" value="websiteRepository"/>
    </bean>

    <bean id="repository.websitemahsup" class="org.jahia.services.uicomponents.bean.contentmanager.Repository">
        <property name="key" value="websiteMashupRepository"/>
    </bean>

    <bean id="repository.shared" class="org.jahia.services.uicomponents.bean.contentmanager.Repository">
        <property name="key" value="sharedRepository"/>
    </bean>

    <bean id="repository.myexternal" class="org.jahia.services.uicomponents.bean.contentmanager.Repository">
        <property name="key" value="myExternalRepository"/>
    </bean>

    <bean id="repository.mymashup" class="org.jahia.services.uicomponents.bean.contentmanager.Repository">
        <property name="key" value="myMashupRepository"/>
    </bean>

    <bean id="repository.my" class="org.jahia.services.uicomponents.bean.contentmanager.Repository">
        <property name="key" value="myRepository"/>
    </bean>

    <bean id="repository.users" class="org.jahia.services.uicomponents.bean.contentmanager.Repository">
        <property name="key" value="usersRepository"/>
    </bean>

    <bean id="repository.category" class="org.jahia.services.uicomponents.bean.contentmanager.Repository">
        <property name="key" value="categoryRepository"/>
    </bean>

    <bean id="repository.tag" class="org.jahia.services.uicomponents.bean.contentmanager.Repository">
        <property name="key" value="tagRepository"/>
    </bean>

    <bean id="repository.remotePublication" class="org.jahia.services.uicomponents.bean.contentmanager.Repository">
        <property name="key" value="remotePublicationsRepository"/>
    </bean>

    <bean id="repository.role" class="org.jahia.services.uicomponents.bean.contentmanager.Repository">
        <property name="key" value="roleRepository"/>
    </bean>

    <bean id="repository.siteRole" class="org.jahia.services.uicomponents.bean.contentmanager.Repository">
        <property name="key" value="siteRoleRepository"/>
    </bean>

    <bean id="repository.site" class="org.jahia.services.uicomponents.bean.contentmanager.Repository">
        <property name="key" value="siteRepository"/>
    </bean>

    <bean id="repository.portletdefinition" class="org.jahia.services.uicomponents.bean.contentmanager.Repository">
        <property name="key" value="portletDefinitionRepository"/>
    </bean>

    <bean id="repository.sharedmashup" class="org.jahia.services.uicomponents.bean.contentmanager.Repository">
        <property name="key" value="sharedMashupRepository"/>
    </bean>


</beans>