
<site jcr:primaryType="jnt:virtualsite" jcr:mixinTypes="jmix:accessControlled"
           xmlns:jcr="http://www.jcp.org/jcr/1.0"
           xmlns:j="http://www.jahia.org/jahia/1.0"
           xmlns:jnt="http://www.jahia.org/jahia/nt/1.0">

    <j:acl jcr:primaryType="jnt:acl">
        <GRANT_jcr_read_g_users j:protected="false" jcr:primaryType="jnt:ace" j:principal="g:users" j:privileges="jcr:read" j:aceType="GRANT"/>
        <GRANT_jcr_write_g_users j:protected="false" jcr:primaryType="jnt:ace" j:principal="g:users" j:privileges="jcr:write" j:aceType="GRANT"/>
        <!--<GRANT_g_users j:protected="false" jcr:primaryType="jnt:ace" j:principal="g:users" j:privileges="jcr:read jcr:write" j:aceType="GRANT"/>-->
        <!--<DENY_g_users j:protected="false" jcr:primaryType="jnt:ace" j:principal="g:users" j:privileges="" j:aceType="DENY"/>-->
    </j:acl>


    <files jcr:primaryType="jnt:folder"/>
    
    <mashups jcr:primaryType="jnt:folder"/>

    <content jcr:primaryType="jnt:folder"/>

    <home jcr:primaryType="jnt:page" />

</site>