<?xml version="1.0"?>

<!DOCTYPE mbeans-descriptors PUBLIC
 "-//Apache Software Foundation//DTD Model MBeans Configuration File"
 "http://jakarta.apache.org/commons/dtds/mbeans-descriptors.dtd">

<!-- Descriptions of JMX MBeans for Jahia -->

<mbeans-descriptors>

  <mbean         name="CacheFactory"
          description="Cache factory"
                 type="org.jahia.services.cache.CacheFactory">

    <attribute   name="serviceName"
          description="The name of the service"
                 type="java.lang.String"/>
    <!--
    <constructor name="CacheFactory"/>
    -->

    <operation   name="flushAllCaches"
          description="Flushes all the caches in the factory"
               impact="ACTION"
           returnType="void">
    </operation>

    <!--
    <operation   name="findServices"
          description="Return all child Services"
               impact="INFO"
           returnType="[Lorg.apache.commons.modeler.demo.Service;"/>

    <operation   name="removeService"
          description="Remove an existing child Service"
               impact="ACTION"
           returnType="void">
      <parameter name="service"
          description="The service to be removed"
                 type="org.apache.commons.modeler.demo.Service"/>
    </operation>
    -->

  </mbean>

  <mbean         name="Cache"
          description="Cache"
                 type="org.jahia.services.cache.Cache">

    <attribute   name="name"
          description="Cache name"
            writeable="false"
                 type="java.lang.String"/>

    <attribute   name="description"
          description="Description"
            writeable="false"
                 type="java.lang.String"/>

    <attribute   name="cacheLimit"
          description="Cache size limit"
                 type="int"/>

    <attribute   name="size"
            getMethod="size"
          description="Current cache size"
            writeable="false"
                 type="int"/>

    <!--
    <constructor name="CacheFactory"/>
    -->

    <operation   name="flush"
          description="Flushes this cache"
               impact="ACTION"
           returnType="void">
    </operation>

    <!--
    <operation   name="findServices"
          description="Return all child Services"
               impact="INFO"
           returnType="[Lorg.apache.commons.modeler.demo.Service;"/>

    <operation   name="removeService"
          description="Remove an existing child Service"
               impact="ACTION"
           returnType="void">
      <parameter name="service"
          description="The service to be removed"
                 type="org.apache.commons.modeler.demo.Service"/>
    </operation>
    -->

  </mbean>


  <mbean         name="JahiaService"
          description="Generic Jahia Service"
                 type="org.jahia.services.JahiaService">
    <attribute   name="serviceName"
          description="The name of the service"
                 type="java.lang.String"/>
  </mbean>

  <mbean         name="JahiaTextFileService"
          description="Bigtext content file handling service"
                 type="org.jahia.services.files.JahiaTextFileService">
  </mbean>

  <mbean         name="JahiaPageService"
          description="Page service"
                 type="org.jahia.services.pages.JahiaPageBaseService">
  </mbean>

  <mbean         name="JahiaPageTemplateService"
          description="Page template service"
                 type="org.jahia.services.pages.JahiaPageTemplateService">
  </mbean>

  <mbean         name="JahiaFieldService"
          description="Field service"
                 type="org.jahia.services.fields.JahiaFieldService">
  </mbean>

  <mbean         name="JahiaApplicationsDispatchingService"
          description="Web application dispatching service"
                 type="org.jahia.services.applications.JahiaApplicationsDispatchingService">
  </mbean>

  <mbean         name="JahiaApplicationsPersistanceService"
          description="Web application metadata persistence service"
                 type="org.jahia.services.applications.JahiaApplicationsPersistanceService">
  </mbean>

  <mbean         name="JahiaApplicationsManagerService"
          description="Web application management service"
                 type="org.jahia.services.applications.JahiaApplicationsManagerService">
  </mbean>

  <mbean         name="JahiaApplicationContextService"
          description="Web application context service"
                 type="org.jahia.services.applications.JahiaApplicationContextService">
  </mbean>

  <mbean         name="JahiaContainersService"
          description="Container service"
                 type="org.jahia.services.containers.JahiaContainersBaseService">
  </mbean>

  <mbean         name="JahiaSearchService"
          description="Search engine service"
                 type="org.jahia.services.search.JahiaSearchService">
  </mbean>

  <mbean         name="JahiaGroupManagerService"
          description="Group manager service"
                 type="org.jahia.services.usermanager.JahiaGroupManagerService">
  </mbean>

  <mbean         name="JahiaACLManagerService"
          description="ACL manager service"
                 type="org.jahia.services.acl.JahiaACLManagerService">
  </mbean>

  <mbean         name="JahiaFetcherService"
          description="Servlet dispatcher that redirects output to String service"
                 type="org.jahia.services.fetchers.JahiaFetcherService">
  </mbean>

  <mbean         name="JahiaTemplatesDeployerService"
          description="Template deployer service"
                 type="org.jahia.services.templates_deployer.JahiaTemplatesDeployerService">
  </mbean>

  <mbean         name="JahiaWebAppsDeployerService"
          description="Web application deployer service"
                 type="org.jahia.services.webapps_deployer.JahiaWebAppsDeployerService">
  </mbean>

  <mbean         name="JahiaFileWatcherService"
          description="File watcher daemon service"
                 type="org.jahia.services.deamons.filewatcher.JahiaFileWatcherService">
  </mbean>

  <mbean         name="JahiaEventService"
          description="Event generation service"
                 type="org.jahia.services.events.JahiaEventGeneratorService">
  </mbean>

  <mbean         name="JahiaAuditLogManagerService"
          description="Event log management service"
                 type="org.jahia.services.audit.JahiaAuditLogManagerService">
  </mbean>

  <mbean         name="JahiaSitesService"
          description="Site management service"
                 type="org.jahia.services.sites.JahiaSitesService">
  </mbean>

  <mbean         name="JahiaSiteUserManagerService"
          description="Site user management service"
                 type="org.jahia.services.usermanager.JahiaSiteUserManagerService">
  </mbean>

  <mbean         name="JahiaSiteGroupManagerService"
          description="Site group management service"
                 type="org.jahia.services.usermanager.JahiaSiteGroupManagerService">
  </mbean>

  <mbean         name="AppsShareService"
          description="Web application sharing management service"
                 type="org.jahia.services.shares.AppsShareService">
  </mbean>

  <mbean         name="CacheServerService"
          description="Output cache service (deprecated)"
                 type="org.jahia.services.htmlcache.CacheServerService">
  </mbean>

  <mbean         name="JahiaHomepagesService"
          description="Home (entry) page management service"
                 type="org.jahia.services.homepages.JahiaHomepagesService">
  </mbean>

  <mbean         name="JahiaVersionService"
          description="Workflow, language and staging resolving service"
                 type="org.jahia.services.version.JahiaVersionService">
  </mbean>

  <mbean         name="JahiaCacheService"
          description="Generic caching (cluster-aware) service"
                 type="org.jahia.services.cache.CacheFactory">
  </mbean>

  <mbean         name="JahiaSiteMapService"
          description="Site map caching service"
                 type="org.jahia.services.sitemap.JahiaSiteMapService">
  </mbean>

  <mbean         name="JahiaHtmlEditorsService"
          description="HTML editors configuration service"
                 type="org.jahia.services.htmleditors.HtmlEditorsBaseService">
  </mbean>

  <mbean         name="JahiaResourceBundleService"
          description="Resource bundle management service"
                 type="org.jahia.resourcebundle.ResourceBundleService">
  </mbean>

  <mbean         name="MailService"
          description="Mail sending service"
                 type="org.jahia.services.mail.MailService">
  </mbean>

  <mbean         name="CategoryService"
          description="Category management service"
                 type="org.jahia.services.categories.CategoryService">
  </mbean>

  <mbean         name="HtmlParserService"
          description="HTML parsing service"
                 type="org.jahia.services.htmlparser.HtmlParserService">
  </mbean>

  <mbean         name="URLRewritingService"
          description="URL rewriting service"
                 type="org.jahia.services.urlrewriting.URLRewritingService">
  </mbean>

  <mbean         name="LockService"
          description="Service that handles the locks on content object"
                 type="org.jahia.services.locks.LockService">
    <attribute   name="serviceName"
          description="The name of the service"
                 type="java.lang.String"/>
  </mbean>

  <mbean         name="JahiaUserManagerService"
          description="User manager service"
                 type="org.jahia.services.usermanager.JahiaUserManagerService">
    <operation   name="lookupUser"
          description="Lookup a user by his unique key"
               impact="ACTION-INFO"
           returnType="org.jahia.services.usermanager.JahiaUser">
      <parameter name="userKey"
          description="User key (format : userlogin + ':' + siteID)"
                 type="java.lang.String" />
    </operation>
  </mbean>

  <mbean         name="JahiaUser"
          description="User"
                 type="org.jahia.services.usermanager.JahiaUser">
    <attribute   name="name"
          description="User name"
                 type="java.lang.String"/>
    <attribute   name="properties"
          description="The user's properties"
                 type="java.util.Properties"/>
  </mbean>


  <mbean         name="SettingsBean"
          description="Jahia Configuration Settings"
                 type="org.jahia.settings.SettingsBean">
    <attribute   name="mimeTypes"
          description="Registered mime types"
                 type="java.util.Properties"/>
    <attribute   name="utf8Encoding"
          description="Use UTF-8 encoding"
                 type="boolean"
                   is="true" />
    <attribute   name="outputCacheActivated"
          description="Use output cache"
                 type="boolean"
                   is="true" />
    <attribute   name="outputCacheDefaultExpirationDelay"
          description="Output cache default expiration delay in milliseconds"
                 type="long" />
    <attribute   name="siteIDInURL"
          description="Force the presence of the site id in the generated URLs"
                 type="boolean"
                   is="true" />
    <attribute   name="appDebugModeOn"
          description="Use the application debugging mode"
                 type="boolean"
                   is="true" />
    <attribute   name="appInheritingJahiaSessionAttributes"
          description="Do the applications have access to Jahia's session attributes ?"
                 type="boolean"
                   is="true" />
    <attribute   name="jahiaWebAppsDeployerBaseURL"
          description="Web applications deployer base URL"
                 type="java.lang.String" />
    <attribute   name="defaultLanguageCode"
          description="Default language code"
                 type="java.lang.String" />
    <attribute   name="aclPreloadCount"
          description="Number of ACLs to preload on Jahia startup (-1 means they will all be loaded)"
                 type="int" />
    <attribute   name="jmsCacheActivated"
          description="Use the JMS cache synchronization mechanism"
                 type="boolean"
                   is="true" />
    <attribute   name="jmsCacheInitialContextFactory"
          description="JMS cache initial context factory class"
                 type="java.lang.String" />
    <attribute   name="jmsCacheInitialContextFactory"
          description="JMS cache context URL"
                 type="java.lang.String" />
    <attribute   name="jmsCacheTopicConnectionFactoryName"
          description="JMS cache TopicConnection factory name"
                 type="java.lang.String" />
    <attribute   name="jmsCacheTopicName"
          description="JMS cache topic name"
                 type="java.lang.String" />
    <attribute   name="buildNumber"
          description="Jahia Build number"
                 type="int" />
    <attribute   name="server"
          description="Web container name"
                 type="java.lang.String" />
    <attribute   name="serverHomeDiskPath"
          description="Web container home disk path"
                 type="java.lang.String" />
    <attribute   name="jahiaWebAppsDiskPath"
          description="Web container applications home disk path"
                 type="java.lang.String" />
    <attribute   name="jahiaTemplatesDiskPath"
          description="Templates home disk path"
                 type="java.lang.String" />
    <attribute   name="jahiaHtmlEditorsDiskPath"
          description="HTML editors home disk path"
                 type="java.lang.String" />
    <attribute   name="jahiaEnginesDiskPath"
          description="Engines home disk path"
                 type="java.lang.String" />
    <attribute   name="jahiaFilesDiskPath"
          description="Files home disk path"
                 type="java.lang.String" />
    <attribute   name="jahiaEtcDiskPath"
          description="etc directory disk path"
                 type="java.lang.String" />
    <attribute   name="jahiaVarDiskPath"
          description="var directory disk path"
                 type="java.lang.String" />
    <attribute   name="jahiaFilesDataDiskPath"
          description="Bigtext file data disk path"
                 type="java.lang.String" />
    <attribute   name="jahiaFilesTemplatesDiskPath"
          description="File templates disk path"
                 type="java.lang.String" />
    <attribute   name="jahiaLdapDiskPath"
          description="LDAP configuration disk path"
                 type="java.lang.String" />
    <attribute   name="jahiaCasDiskPath"
          description="CAS configuration disk path"
                 type="java.lang.String" />
    <attribute   name="jahiaOutputCacheConfigDiskPath"
          description="Output cache configuration disk path"
                 type="java.lang.String" />
    <attribute   name="jahiaNewTemplatesDiskPath"
          description="New templates deployment disk path"
                 type="java.lang.String" />
    <attribute   name="jahiaSharedTemplatesDiskPath"
          description="Templates shared between sites disk path"
                 type="java.lang.String" />
    <attribute   name="componentsDiskPath"
          description="Web applications disk path"
                 type="java.lang.String" />
    <attribute   name="jahiaTemplatesHttpPath"
          description="Templates http path"
                 type="java.lang.String" />
    <attribute   name="jahiaEnginesHttpPath"
          description="Engines http path"
                 type="java.lang.String" />
    <attribute   name="jsHttpPath"
          description="Javascript http path"
                 type="java.lang.String" />
    <attribute   name="jspContext"
          description="JSP context"
                 type="java.lang.String" />
    <attribute   name="htmlEditorsContext"
          description="HTML editors context"
                 type="java.lang.String" />
    <attribute   name="templatesContext"
          description="Templates context"
                 type="java.lang.String" />
    <attribute   name="enginesContext"
          description="Engines context"
                 type="java.lang.String" />
    <attribute   name="javascriptContext"
          description="Javascript context"
                 type="java.lang.String" />
    <attribute   name="jahiaWebAppsAutoDeploy"
          description="Use web applications automatic deployment mode"
                 type="int" />
    <attribute   name="jahiaTemplatesAutoDeploy"
          description="Use templates automatic deployment mode"
                 type="int" />
    <attribute   name="classDiskPath"
          description="Class disk path"
                 type="java.lang.String" />
    <attribute   name="jahiaFileRepositoryDiskPath"
          description="File repository disk path"
                 type="java.lang.String" />
    <attribute   name="jahiaFilesBigTextDiskPath"
          description="Bigtext data repository disk path"
                 type="java.lang.String" />
    <attribute   name="jahiaFilesDiskPath"
          description="Uploaded files repository disk path"
                 type="java.lang.String" />
    <attribute   name="jahiaFileUploadMaxSize"
          description="Uploaded files maximum size"
                 type="int" />
    <attribute   name="jahiaHomeDiskPath"
          description="Home disk path"
                 type="java.lang.String" />
    <attribute   name="jahiaHostHttpPath"
          description="Host HTTP path"
                 type="java.lang.String" />
    <attribute   name="jahiaJavaScriptDiskPath"
          description="Javascript disk path"
                 type="java.lang.String" />
    <attribute   name="jahiaJavaScriptHttpPath"
          description="Javascript HTTP path"
                 type="java.lang.String" />
    <attribute   name="jahiaJspDiskPath"
          description="JSP disk path"
                 type="java.lang.String" />
    <attribute   name="jahiaMaxCachedValues"
          description="Maximum sizes for caches"
                 type="java.util.HashMap" />
    <attribute   name="jahiaNewWebAppsDiskPath"
          description="Web applications deployment disk path"
                 type="java.lang.String" />
    <attribute   name="locksActivated"
          description="Use locks on content objects"
                 type="boolean"
                   is="true" />
    <attribute   name="mail_administrator"
          description="Email notification destination email address"
                 type="java.lang.String" />
    <attribute   name="mail_from"
          description="Email notification sender name"
                 type="java.lang.String" />
    <attribute   name="mail_paranoia"
          description="Email notification verbosity level"
                 type="int" />
    <attribute   name="mail_server"
          description="Email notification SMTP server hostname"
                 type="java.lang.String" />
    <attribute   name="mLicenseFilename"
          description="License file name"
                 type="java.lang.String" />
    <attribute   name="jmxHTTPAdaptorActivated"
          description="Use JMX HTTP Adaptor"
                 type="boolean"
                   is="true" />
    <attribute   name="jmxHTTPAuthorizationPassword"
          description="JMX HTTP Adaptor authorization password"
                 type="java.lang.String" />
    <attribute   name="jmxHTTPAuthorizationUser"
          description="JMX HTTP Adaptor authorization user name"
                 type="java.lang.String" />
    <attribute   name="jmxHTTPAutorizationMode"
          description="JMX HTTP Adaptor authorization mode"
                 type="java.lang.String" />
    <attribute   name="jmxHTTPHostname"
          description="JMX HTTP Adaptor hostname (localhost listens only on loopback, 0.0.0.0 listens on all interfaces)"
                 type="java.lang.String" />
    <attribute   name="jmxHTTPPort"
          description="JMX HTTP Adaptor port"
                 type="int" />
    <attribute   name="jmxHTTPProcessorNameString"
          description="JMX HTTP Adaptor processor name string"
                 type="java.lang.String" />
    <attribute   name="jmxHTTPSocketFactoryNameString"
          description="JMX HTTP Adaptor socket factory name string"
                 type="java.lang.String" />
    <attribute   name="jmxRMIAdaptorActivated"
          description="Use JMX RMI Adaptor"
                 type="boolean"
                   is="true" />
    <attribute   name="jmxXSLProcessorActivated"
          description="Use JMX XSL Processor"
                 type="boolean"
                   is="true" />
    <attribute   name="jmxRMISSLServerSocketFactoryActivated"
          description="Use RMI SSL server socket factory"
                 type="boolean"
                   is="true" />
    <attribute   name="jmxRMISSLServerSocketFactoryKeyStoreName"
          description="JMX RMI SSL server socket factory keytore name"
                 type="java.lang.String" />
    <attribute   name="jmxRMISSLServerSocketFactoryKeyStorePassword"
          description="JMX RMI SSL server socket factory keytore password"
                 type="java.lang.String" />
    <attribute   name="jmxRMISSLServerSocketFactoryKeyManagerPassword"
          description="JMX RMI SSL server socket factory key manager password"
                 type="java.lang.String" />
  </mbean>

</mbeans-descriptors>
